cli/__init__.py
cli/d6tpipe.py
d6tpipe/__init__.py
d6tpipe/api.py
d6tpipe/exceptions.py
d6tpipe/pipe.py
d6tpipe/tinydb_serializers.py
d6tpipe/http_client/__init__.py
d6tpipe/http_client/client.py
d6tpipe/http_client/exceptions.py
d6tpipe/luigi/__init__.py
d6tpipe/luigi/ftp.py
d6tpipe/luigi/s3.py
d6tpipe/utils/__init__.py
d6tpipe/utils/utils.py
d6tpipe-1.2.7.dist-info/LICENSE
d6tpipe-1.2.7.dist-info/METADATA
d6tpipe-1.2.7.dist-info/WHEEL
d6tpipe-1.2.7.dist-info/entry_points.txt
d6tpipe-1.2.7.dist-info/top_level.txt
d6tpipe-1.2.7.dist-info/RECORD
