Metadata-Version: 2.1
Name: d6tpipe
Version: 1.2.7
Summary: d6tpipe is a python library which makes it easier to exchange data
Home-page: https://github.com/d6t/d6tpipe
Author: DataBolt Team
Author-email: support@databolt.tech
License: MIT
Keywords: d6tpipe,data-pipes
Platform: UNKNOWN
Requires-Python: >=3.5
Requires-Dist: luigi
Requires-Dist: tinydb
Requires-Dist: boto3
Requires-Dist: botocore
Requires-Dist: tinydb-serialization
Requires-Dist: cachetools
Requires-Dist: pyjwt
Requires-Dist: pyyaml
Requires-Dist: tqdm
Requires-Dist: Click
Requires-Dist: d6tcollect
Provides-Extra: ftp
Requires-Dist: pysftp ; extra == 'ftp'
Requires-Dist: pyftpsync ; extra == 'ftp'
